dascore/__init__.py
dascore/compat.py
dascore/constants.py
dascore/data_registry.txt
dascore/examples.py
dascore/exceptions.py
dascore/units.py
dascore/version.py
dascore/clients/__init__.py
dascore/clients/dirspool.py
dascore/clients/filespool.py
dascore/core/__init__.py
dascore/core/attrs.py
dascore/core/coordmanager.py
dascore/core/coords.py
dascore/core/patch.py
dascore/core/spool.py
dascore/io/__init__.py
dascore/io/core.py
dascore/io/indexer.py
dascore/io/ap_sensing/__init__.py
dascore/io/ap_sensing/core.py
dascore/io/ap_sensing/utils.py
dascore/io/dasdae/__init__.py
dascore/io/dasdae/core.py
dascore/io/dasdae/utils.py
dascore/io/dashdf5/__init__.py
dascore/io/dashdf5/core.py
dascore/io/dashdf5/utils.py
dascore/io/febus/__init__.py
dascore/io/febus/core.py
dascore/io/febus/utils.py
dascore/io/gdr/__init__.py
dascore/io/gdr/core.py
dascore/io/gdr/utils_das.py
dascore/io/h5simple/__init__.py
dascore/io/h5simple/core.py
dascore/io/h5simple/utils.py
dascore/io/neubrex/__init__.py
dascore/io/neubrex/core.py
dascore/io/neubrex/utils_das.py
dascore/io/neubrex/utils_rfs.py
dascore/io/optodas/__init__.py
dascore/io/optodas/core.py
dascore/io/optodas/utils.py
dascore/io/pickle/__init__.py
dascore/io/pickle/core.py
dascore/io/prodml/__init__.py
dascore/io/prodml/core.py
dascore/io/prodml/utils.py
dascore/io/rsf/__init__.py
dascore/io/rsf/core.py
dascore/io/segy/__init__.py
dascore/io/segy/core.py
dascore/io/segy/utils.py
dascore/io/sentek/__init__.py
dascore/io/sentek/core.py
dascore/io/sentek/utils.py
dascore/io/silixah5/__init__.py
dascore/io/silixah5/core.py
dascore/io/silixah5/utils.py
dascore/io/sintela_binary/__init__.py
dascore/io/sintela_binary/core.py
dascore/io/sintela_binary/utils.py
dascore/io/tdms/__init__.py
dascore/io/tdms/core.py
dascore/io/tdms/utils.py
dascore/io/terra15/__init__.py
dascore/io/terra15/core.py
dascore/io/terra15/utils.py
dascore/io/wav/__init__.py
dascore/io/wav/core.py
dascore/io/xml_binary/__init__.py
dascore/io/xml_binary/core.py
dascore-0.1.13.dist-info/METADATA
dascore-0.1.13.dist-info/WHEEL
dascore-0.1.13.dist-info/entry_points.txt
dascore-0.1.13.dist-info/top_level.txt
dascore-0.1.13.dist-info/RECORD
