Metadata-Version: 2.4
Name: dascore
Version: 0.1.13
Summary: A python library for distributed fiber optic sensing
Author-email: Derrick Chambers <chambers.ja.derrick@gmail.com>
License: dascore is licensed under LGPL version 3 license:
Project-URL: Bug Tracker, https://github.com/DASDAE/dascore/issues
Project-URL: Documentation, https://dascore.org
Project-URL: Homepage, https://dascore.org
Keywords: geophysics,distributed-acoustic-sensing
Classifier: Development Status :: 4 - Beta
Classifier: License :: OSI Approved :: GNU Lesser General Public License v3 or later (LGPLv3+)
Classifier: Topic :: Scientific/Engineering
Classifier: Programming Language :: Python :: 3.10
Classifier: Programming Language :: Python :: 3.11
Classifier: Programming Language :: Python :: 3.12
Classifier: Programming Language :: Python :: 3.13
Classifier: Programming Language :: Python :: 3.14
Requires-Python: >=3.10
Requires-Dist: h5py
Requires-Dist: matplotlib>=3.8
Requires-Dist: numpy>=1.24
Requires-Dist: packaging
Requires-Dist: pandas>=2.0
Requires-Dist: pooch>=1.2
Requires-Dist: pydantic>2.1
Requires-Dist: rich
Requires-Dist: tables>=3.7
Requires-Dist: typing_extensions>=4.12
Requires-Dist: pint
Requires-Dist: scipy>=1.15
Provides-Extra: extras
Requires-Dist: xarray; extra == "extras"
Requires-Dist: findiff; extra == "extras"
Requires-Dist: obspy; extra == "extras"
Requires-Dist: numba; extra == "extras"
Requires-Dist: segyio; extra == "extras"
Requires-Dist: bottleneck; extra == "extras"
Provides-Extra: docs
Requires-Dist: jinja2; extra == "docs"
Requires-Dist: ipywidgets; extra == "docs"
Requires-Dist: tabulate; extra == "docs"
Provides-Extra: test
Requires-Dist: coverage<8,>=7.4; extra == "test"
Requires-Dist: pytest-cov>=4; extra == "test"
Requires-Dist: pre-commit; extra == "test"
Requires-Dist: pytest; extra == "test"
Requires-Dist: pytest-codeblocks; extra == "test"
Requires-Dist: pytest-cov; extra == "test"
Requires-Dist: twine; extra == "test"
Provides-Extra: profile-base
Requires-Dist: pytest-codspeed; extra == "profile-base"
Requires-Dist: pytest-profiling; extra == "profile-base"
Provides-Extra: all
Requires-Dist: dascore[extras]; extra == "all"
Provides-Extra: profile
Requires-Dist: dascore[test]; extra == "profile"
Requires-Dist: dascore[profile_base]; extra == "profile"
Provides-Extra: dev
Requires-Dist: dascore[test]; extra == "dev"
Requires-Dist: dascore[docs]; extra == "dev"
Requires-Dist: dascore[profile_base]; extra == "dev"
Requires-Dist: dascore[extras]; extra == "dev"
